ncbiget.py
ncbidare-1.0.0.dist-info/LICENSE
ncbidare-1.0.0.dist-info/METADATA
ncbidare-1.0.0.dist-info/WHEEL
ncbidare-1.0.0.dist-info/top_level.txt
ncbidare-1.0.0.dist-info/RECORD
