Metadata-Version: 2.1
Name: ncbidare
Version: 1.0.0
Summary: Fetch NCBI data efficiently
Home-page: https://github.com/riddhisera/microbio
Author: Riddhi Sera
Author-email: riddhisera@gmail.com
License: UNKNOWN
Platform: UNKNOWN
Classifier: Programming Language :: Python :: 3
Classifier: Programming Language :: Python :: 3.7
Classifier: Programming Language :: Python :: 3.8
Classifier: License :: OSI Approved :: GNU General Public License v3 (GPLv3)
Classifier: Operating System :: OS Independent
Requires-Dist: biopython (~=1.78)
Provides-Extra: dev
Requires-Dist: pytest (>=3.7) ; extra == 'dev'
